README.txt
rules.xml
setup.cfg
setup.py
docs/HISTORY.txt
docs/INSTALL.txt
docs/LICENSE.GPL
docs/LICENSE.txt
xdvtheme/__init__.py
xdvtheme.inventions.egg-info/PKG-INFO
xdvtheme.inventions.egg-info/SOURCES.txt
xdvtheme.inventions.egg-info/dependency_links.txt
xdvtheme.inventions.egg-info/entry_points.txt
xdvtheme.inventions.egg-info/namespace_packages.txt
xdvtheme.inventions.egg-info/not-zip-safe
xdvtheme.inventions.egg-info/paster_plugins.txt
xdvtheme.inventions.egg-info/top_level.txt
xdvtheme/inventions/__init__.py
xdvtheme/inventions/configure.zcml
xdvtheme/inventions/tests.py
xdvtheme/inventions/profiles/default/skins.xml
xdvtheme/inventions/skins/xdvtheme.inventions/bg.gif
xdvtheme/inventions/skins/xdvtheme.inventions/bg_header_top.gif
xdvtheme/inventions/skins/xdvtheme.inventions/colbg.gif
xdvtheme/inventions/skins/xdvtheme.inventions/ie.css
xdvtheme/inventions/skins/xdvtheme.inventions/index.html
xdvtheme/inventions/skins/xdvtheme.inventions/main_img.jpg
xdvtheme/inventions/skins/xdvtheme.inventions/orange_bullet.gif
xdvtheme/inventions/skins/xdvtheme.inventions/style-fixed.css
xdvtheme/inventions/skins/xdvtheme.inventions/style.css