Metadata-Version: 1.0
Name: xdvtheme.inventions
Version: 1.0
Summary: A xdvtheme for Plone
Home-page: http://menttes.com
Author: Roberto Allende
Author-email: rover@menttes.com
License: GPL
Keywords: theme skin Plone xdv menttes
Platform: UNKNOWN
Classifier: Framework :: Plone
Classifier: Programming Language :: Python
